equation_solver/__init__.py
equation_solver/linear.py
equation_solver/nonlinear.py
hp23005equation_solver-0.1.1.dist-info/METADATA
hp23005equation_solver-0.1.1.dist-info/WHEEL
hp23005equation_solver-0.1.1.dist-info/top_level.txt
hp23005equation_solver-0.1.1.dist-info/RECORD
