Metadata-Version: 2.4
Name: hp23005equation-solver
Version: 0.1.1
Summary: Librería para resolver ecuaciones lineales y no lineales con métodos numéricos
Home-page: https://github.com/HP23005/equation-solver
Author: HP23005
Author-email: hp23005@ues.edu.sv
Classifier: Development Status :: 3 - Alpha
Classifier: Programming Language :: Python :: 3
Classifier: License :: OSI Approved :: MIT License
Classifier: Operating System :: OS Independent
Classifier: Intended Audience :: Education
Classifier: Topic :: Scientific/Engineering :: Mathematics
Requires-Python: >=3.7
Requires-Dist: numpy>=1.18
Requires-Dist: scipy>=1.4
Dynamic: author
Dynamic: author-email
Dynamic: classifier
Dynamic: description
Dynamic: description-content-type
Dynamic: home-page
Dynamic: requires-dist
Dynamic: requires-python
Dynamic: summary
